owclient/__init__.py
owclient/owclient.py
owclient/py.typed
owclient/devices/__init__.py
owclient/devices/device.py
owclient/devices/ds18b20.py
owclient/devices/ds18s20.py
owclient/devices/py.typed
owclient/devices/thermometer.py
owclient/exc/__init__.py
owclient/exc/couldnotconnecterror.py
owclient/exc/couldnotloaddeviceerror.py
owclient/exc/couldnotloaddeviceserror.py
owclient/exc/couldnotreaderror.py
owclient/exc/couldnotwriteerror.py
owclient/exc/incorrectprecisionerror.py
owclient/exc/precisionnotseterror.py
owclient/exc/py.typed
owclient/exc/unrecognizeddeviceerror.py
owclient-0.1.8.dist-info/LICENSE
owclient-0.1.8.dist-info/METADATA
owclient-0.1.8.dist-info/WHEEL
owclient-0.1.8.dist-info/top_level.txt
owclient-0.1.8.dist-info/RECORD
