Metadata-Version: 2.1
Name: owclient
Version: 0.1.8
Summary: A light layer to use OWFS and pyownet with a more OOP approach.
Home-page: https://gitlab.com/fcomabella/ow-client
Author: Ferran Comabella
Author-email: ferran@gmail.com
License: UNKNOWN
Platform: UNKNOWN
Requires-Python: >=3.8,<4.0
Requires-Dist: pyownet (<0.11.0,>=0.10.0)
